django_form_action/__init__.py
django_form_action/decorators.py
django_form_action/py.typed
django_form_action/templates/django_form_action/intermediate.html
django_form_action-3.0.1.dist-info/licenses/LICENSE
django_form_action-3.0.1.dist-info/METADATA
django_form_action-3.0.1.dist-info/WHEEL
django_form_action-3.0.1.dist-info/top_level.txt
django_form_action-3.0.1.dist-info/RECORD
