Metadata-Version: 2.4
Name: django-form-action
Version: 3.0.1
Summary: Django action with an intermediate page to parse data from a form
Author-email: Pradish Bijukchhe <pradish@sandbox.com.np>
License: Copyright (c) 2024 Pradish Bijukchhe
Project-URL: Homepage, https://github.com/sandbox-pokhara/django-form-action
Project-URL: Issues, https://github.com/sandbox-pokhara/django-form-action/issues
Classifier: Programming Language :: Python :: 3
Requires-Python: >=3
License-File: LICENSE
Requires-Dist: django
Dynamic: license-file
